<?xml version='1.0' encoding='UTF-8'?><S:Envelope xmlns:S="http://schemas.xmlsoap.org/soap/envelope/"><S:Header><wsse:Security xmlns:wsse="http://docs.oasis-open.org/wss/2004/01/oasis-200401-wss-wssecurity-secext-1.0.xsd" S:mustUnderstand="1"><wsu:Timestamp xmlns:wsu="http://docs.oasis-open.org/wss/2004/01/oasis-200401-wss-wssecurity-utility-1.0.xsd"><wsu:Created>2017-10-12T18:10:44Z</wsu:Created><wsu:Expires>2017-10-12T18:11:44Z</wsu:Expires></wsu:Timestamp></wsse:Security></S:Header><S:Body><ConsultarEdocumentResponse xmlns="http://www.ventanillaunica.gob.mx/ConsultarEdocument/" xmlns:ns2="http://www.ventanillaunica.gob.mx/cove/ws/oxml/"><response><mensaje>La consulta se realizó exitosamente</mensaje><contieneError>false</contieneError><resultadoBusqueda><cove><eDocument>COVE1723WG4U8</eDocument><tipoOperacion>TOCE.IMP</tipoOperacion><numeroFacturaRelacionFacturas>43942878</numeroFacturaRelacionFacturas><relacionFacturas>0</relacionFacturas><automotriz>0</automotriz><fechaExpedicion>2017-08-16-05:00</fechaExpedicion><tipoFigura>1</tipoFigura><patentesAduanales><patenteAduanal>1618</patenteAduanal></patentesAduanales><rfcsConsulta><rfcConsulta>GSY110601FD4</rfcConsulta></rfcsConsulta><observaciones>OTROS GASTOS: $ 90.28</observaciones><facturas><factura><certificadoOrigen>0</certificadoOrigen><subdivision>0</subdivision><mercancias><mercancia><descripcionGenerica>CHUMACERAS CON RODAMIENTOS</descripcionGenerica><claveUnidadMedida>EA</claveUnidadMedida><tipoMoneda>USD</tipoMoneda><cantidad>6</cantidad><valorUnitario>28.38</valorUnitario><valorTotal>170.28</valorTotal><valorDolares>170.28</valorDolares></mercancia><mercancia><descripcionGenerica>RIEL DE ALUMINIO</descripcionGenerica><claveUnidadMedida>EA</claveUnidadMedida><tipoMoneda>USD</tipoMoneda><cantidad>3</cantidad><valorUnitario>46.16</valorUnitario><valorTotal>138.48</valorTotal><valorDolares>138.48</valorDolares></mercancia><mercancia><descripcionGenerica>CHUMACERAS CON RODAMIENTOS</descripcionGenerica><claveUnidadMedida>EA</claveUnidadMedida><tipoMoneda>USD</tipoMoneda><cantidad>54</cantidad><valorUnitario>11.67</valorUnitario><valorTotal>630.18</valorTotal><valorDolares>630.18</valorDolares></mercancia><mercancia><descripcionGenerica>ARMELLAS</descripcionGenerica><claveUnidadMedida>PK</claveUnidadMedida><tipoMoneda>USD</tipoMoneda><cantidad>54</cantidad><valorUnitario>3.14</valorUnitario><valorTotal>169.56</valorTotal><valorDolares>169.56</valorDolares></mercancia></mercancias></factura></facturas><emisor><tipoIdentificador>0</tipoIdentificador><identificacion>36-1458720</identificacion><nombre>MCMASTER-CARR SUPPLY COMPANY</nombre><domicilio><calle>NORWALK BLVD</calle><numeroExterior>9630</numeroExterior><municipio>SANTA FE</municipio><entidadFederativa>CA</entidadFederativa><pais>USA</pais><codigoPostal>90670</codigoPostal></domicilio></emisor><destinatario><tipoIdentificador>1</tipoIdentificador><identificacion>GSY110601FD4</identificacion><nombre>GENESIS SYSTEMS GROUP MEXICO S DE RL DE CV</nombre><domicilio><calle>TOMAS ALBA EDISON</calle><numeroExterior>7</numeroExterior><colonia>ZONA IND. VALLE DE ORO</colonia><municipio>SAN JUAN DEL RIO</municipio><entidadFederativa>QUERETARO</entidadFederativa><pais>MEX</pais><codigoPostal>76803</codigoPostal></domicilio></destinatario></cove></resultadoBusqueda></response></ConsultarEdocumentResponse></S:Body></S:Envelope>