<?xml version='1.0' encoding='UTF-8'?><S:Envelope xmlns:S="http://schemas.xmlsoap.org/soap/envelope/"><S:Header><wsse:Security xmlns:wsse="http://docs.oasis-open.org/wss/2004/01/oasis-200401-wss-wssecurity-secext-1.0.xsd" S:mustUnderstand="1"><wsu:Timestamp xmlns:wsu="http://docs.oasis-open.org/wss/2004/01/oasis-200401-wss-wssecurity-utility-1.0.xsd"><wsu:Created>2017-09-27T14:44:38Z</wsu:Created><wsu:Expires>2017-09-27T14:45:38Z</wsu:Expires></wsu:Timestamp></wsse:Security></S:Header><S:Body><ConsultarEdocumentResponse xmlns="http://www.ventanillaunica.gob.mx/ConsultarEdocument/" xmlns:ns2="http://www.ventanillaunica.gob.mx/cove/ws/oxml/"><response><mensaje>La consulta se realizó exitosamente</mensaje><contieneError>false</contieneError><resultadoBusqueda><cove><eDocument>COVE12056PHL3</eDocument><tipoOperacion>TOCE.IMP</tipoOperacion><numeroFacturaRelacionFacturas>57118961.001</numeroFacturaRelacionFacturas><relacionFacturas>0</relacionFacturas><automotriz>0</automotriz><fechaExpedicion>2012-09-14-05:00</fechaExpedicion><tipoFigura>1</tipoFigura><patentesAduanales><patenteAduanal>3663</patenteAduanal></patentesAduanales><rfcsConsulta><rfcConsulta>GSY110601FD4</rfcConsulta></rfcsConsulta><observaciones></observaciones><facturas><factura><certificadoOrigen>0</certificadoOrigen><subdivision>0</subdivision><mercancias><mercancia><descripcionGenerica>CONTACTORES</descripcionGenerica><claveUnidadMedida>6</claveUnidadMedida><tipoMoneda>USD</tipoMoneda><cantidad>1</cantidad><valorUnitario>142.57</valorUnitario><valorTotal>142.57</valorTotal><valorDolares>142.57</valorDolares></mercancia><mercancia><descripcionGenerica>CONECTORES</descripcionGenerica><claveUnidadMedida>6</claveUnidadMedida><tipoMoneda>USD</tipoMoneda><cantidad>9</cantidad><valorUnitario>2.04</valorUnitario><valorTotal>18.36</valorTotal><valorDolares>18.36</valorDolares></mercancia><mercancia><descripcionGenerica>PIEZAS AISLANTES</descripcionGenerica><claveUnidadMedida>6</claveUnidadMedida><tipoMoneda>USD</tipoMoneda><cantidad>20</cantidad><valorUnitario>0.33</valorUnitario><valorTotal>6.6</valorTotal><valorDolares>6.6</valorDolares></mercancia><mercancia><descripcionGenerica>PIEZAS AISLANTES</descripcionGenerica><claveUnidadMedida>6</claveUnidadMedida><tipoMoneda>USD</tipoMoneda><cantidad>10</cantidad><valorUnitario>0.36</valorUnitario><valorTotal>3.6</valorTotal><valorDolares>3.6</valorDolares></mercancia><mercancia><descripcionGenerica>CONECTORES</descripcionGenerica><claveUnidadMedida>6</claveUnidadMedida><tipoMoneda>USD</tipoMoneda><cantidad>12</cantidad><valorUnitario>0.42</valorUnitario><valorTotal>5.04</valorTotal><valorDolares>5.04</valorDolares></mercancia><mercancia><descripcionGenerica>CONECTORES</descripcionGenerica><claveUnidadMedida>6</claveUnidadMedida><tipoMoneda>USD</tipoMoneda><cantidad>5</cantidad><valorUnitario>6.77</valorUnitario><valorTotal>33.85</valorTotal><valorDolares>33.85</valorDolares></mercancia><mercancia><descripcionGenerica>CONECTORES</descripcionGenerica><claveUnidadMedida>6</claveUnidadMedida><tipoMoneda>USD</tipoMoneda><cantidad>1</cantidad><valorUnitario>6.04</valorUnitario><valorTotal>6.04</valorTotal><valorDolares>6.04</valorDolares></mercancia><mercancia><descripcionGenerica>CONECTORES</descripcionGenerica><claveUnidadMedida>6</claveUnidadMedida><tipoMoneda>USD</tipoMoneda><cantidad>200</cantidad><valorUnitario>0.48</valorUnitario><valorTotal>96</valorTotal><valorDolares>96</valorDolares></mercancia><mercancia><descripcionGenerica>CONECTORES</descripcionGenerica><claveUnidadMedida>6</claveUnidadMedida><tipoMoneda>USD</tipoMoneda><cantidad>30</cantidad><valorUnitario>0.77</valorUnitario><valorTotal>23.1</valorTotal><valorDolares>23.1</valorDolares></mercancia><mercancia><descripcionGenerica>CONECTORES</descripcionGenerica><claveUnidadMedida>6</claveUnidadMedida><tipoMoneda>USD</tipoMoneda><cantidad>10</cantidad><valorUnitario>2.96</valorUnitario><valorTotal>29.6</valorTotal><valorDolares>29.6</valorDolares></mercancia><mercancia><descripcionGenerica>PIEZAS AISLANTES</descripcionGenerica><claveUnidadMedida>6</claveUnidadMedida><tipoMoneda>USD</tipoMoneda><cantidad>4</cantidad><valorUnitario>0.79</valorUnitario><valorTotal>3.16</valorTotal><valorDolares>3.16</valorDolares></mercancia><mercancia><descripcionGenerica>PIEZAS AISLANTES</descripcionGenerica><claveUnidadMedida>6</claveUnidadMedida><tipoMoneda>USD</tipoMoneda><cantidad>1</cantidad><valorUnitario>3.32</valorUnitario><valorTotal>3.32</valorTotal><valorDolares>3.32</valorDolares></mercancia><mercancia><descripcionGenerica>CONECTORES</descripcionGenerica><claveUnidadMedida>6</claveUnidadMedida><tipoMoneda>USD</tipoMoneda><cantidad>1</cantidad><valorUnitario>46.75</valorUnitario><valorTotal>46.75</valorTotal><valorDolares>46.75</valorDolares></mercancia><mercancia><descripcionGenerica>CONTROLADOR DE VELOCIDADES</descripcionGenerica><claveUnidadMedida>6</claveUnidadMedida><tipoMoneda>USD</tipoMoneda><cantidad>1</cantidad><valorUnitario>24.59</valorUnitario><valorTotal>24.59</valorTotal><valorDolares>24.59</valorDolares></mercancia><mercancia><descripcionGenerica>MODULOS DE CONTROL.</descripcionGenerica><claveUnidadMedida>6</claveUnidadMedida><tipoMoneda>USD</tipoMoneda><cantidad>2</cantidad><valorUnitario>46.39</valorUnitario><valorTotal>92.78</valorTotal><valorDolares>92.78</valorDolares></mercancia><mercancia><descripcionGenerica>MODULOS DE CONTROL.</descripcionGenerica><claveUnidadMedida>6</claveUnidadMedida><tipoMoneda>USD</tipoMoneda><cantidad>1</cantidad><valorUnitario>190.68</valorUnitario><valorTotal>190.68</valorTotal><valorDolares>190.68</valorDolares></mercancia><mercancia><descripcionGenerica>MODULOS DE CONTROL.</descripcionGenerica><claveUnidadMedida>6</claveUnidadMedida><tipoMoneda>USD</tipoMoneda><cantidad>3</cantidad><valorUnitario>52.28</valorUnitario><valorTotal>156.84</valorTotal><valorDolares>156.84</valorDolares></mercancia><mercancia><descripcionGenerica>TERMINAL</descripcionGenerica><claveUnidadMedida>6</claveUnidadMedida><tipoMoneda>USD</tipoMoneda><cantidad>6</cantidad><valorUnitario>8</valorUnitario><valorTotal>48</valorTotal><valorDolares>48</valorDolares></mercancia><mercancia><descripcionGenerica>PANEL DE CONTROL.</descripcionGenerica><claveUnidadMedida>6</claveUnidadMedida><tipoMoneda>USD</tipoMoneda><cantidad>1</cantidad><valorUnitario>1019.49</valorUnitario><valorTotal>1019.49</valorTotal><valorDolares>1019.49</valorDolares></mercancia><mercancia><descripcionGenerica>APARATOS PARA PROTECCION DE CIRCUITOS ELECTRICOS.</descripcionGenerica><claveUnidadMedida>6</claveUnidadMedida><tipoMoneda>USD</tipoMoneda><cantidad>1</cantidad><valorUnitario>45.23</valorUnitario><valorTotal>45.23</valorTotal><valorDolares>45.23</valorDolares></mercancia><mercancia><descripcionGenerica>RIELES DE ACERO.</descripcionGenerica><claveUnidadMedida>6</claveUnidadMedida><tipoMoneda>USD</tipoMoneda><cantidad>6</cantidad><valorUnitario>7.91</valorUnitario><valorTotal>47.46</valorTotal><valorDolares>47.46</valorDolares></mercancia><mercancia><descripcionGenerica>PANEL DE CONTROL.</descripcionGenerica><claveUnidadMedida>6</claveUnidadMedida><tipoMoneda>USD</tipoMoneda><cantidad>1</cantidad><valorUnitario>2308.76</valorUnitario><valorTotal>2308.76</valorTotal><valorDolares>2308.76</valorDolares></mercancia><mercancia><descripcionGenerica>CONTACTORES</descripcionGenerica><claveUnidadMedida>6</claveUnidadMedida><tipoMoneda>USD</tipoMoneda><cantidad>1</cantidad><valorUnitario>22.94</valorUnitario><valorTotal>22.94</valorTotal><valorDolares>22.94</valorDolares></mercancia><mercancia><descripcionGenerica>CONTACTORES</descripcionGenerica><claveUnidadMedida>6</claveUnidadMedida><tipoMoneda>USD</tipoMoneda><cantidad>1</cantidad><valorUnitario>13.38</valorUnitario><valorTotal>13.38</valorTotal><valorDolares>13.38</valorDolares></mercancia><mercancia><descripcionGenerica>CONTACTORES</descripcionGenerica><claveUnidadMedida>6</claveUnidadMedida><tipoMoneda>USD</tipoMoneda><cantidad>6</cantidad><valorUnitario>8.07</valorUnitario><valorTotal>48.42</valorTotal><valorDolares>48.42</valorDolares></mercancia><mercancia><descripcionGenerica>CONTACTORES</descripcionGenerica><claveUnidadMedida>6</claveUnidadMedida><tipoMoneda>USD</tipoMoneda><cantidad>1</cantidad><valorUnitario>16.27</valorUnitario><valorTotal>16.27</valorTotal><valorDolares>16.27</valorDolares></mercancia><mercancia><descripcionGenerica>CONTACTORES</descripcionGenerica><claveUnidadMedida>6</claveUnidadMedida><tipoMoneda>USD</tipoMoneda><cantidad>1</cantidad><valorUnitario>16.28</valorUnitario><valorTotal>16.28</valorTotal><valorDolares>16.28</valorDolares></mercancia><mercancia><descripcionGenerica>ENSAMBLES</descripcionGenerica><claveUnidadMedida>6</claveUnidadMedida><tipoMoneda>USD</tipoMoneda><cantidad>3</cantidad><valorUnitario>5.72</valorUnitario><valorTotal>17.16</valorTotal><valorDolares>17.16</valorDolares></mercancia><mercancia><descripcionGenerica>ENSAMBLES</descripcionGenerica><claveUnidadMedida>6</claveUnidadMedida><tipoMoneda>USD</tipoMoneda><cantidad>1</cantidad><valorUnitario>4.7</valorUnitario><valorTotal>4.7</valorTotal><valorDolares>4.7</valorDolares></mercancia><mercancia><descripcionGenerica>BOTONES</descripcionGenerica><claveUnidadMedida>6</claveUnidadMedida><tipoMoneda>USD</tipoMoneda><cantidad>1</cantidad><valorUnitario>12.57</valorUnitario><valorTotal>12.57</valorTotal><valorDolares>12.57</valorDolares></mercancia><mercancia><descripcionGenerica>ENSAMBLES</descripcionGenerica><claveUnidadMedida>6</claveUnidadMedida><tipoMoneda>USD</tipoMoneda><cantidad>2</cantidad><valorUnitario>12.5</valorUnitario><valorTotal>25</valorTotal><valorDolares>25</valorDolares></mercancia><mercancia><descripcionGenerica>ENSAMBLES</descripcionGenerica><claveUnidadMedida>6</claveUnidadMedida><tipoMoneda>USD</tipoMoneda><cantidad>1</cantidad><valorUnitario>19.24</valorUnitario><valorTotal>19.24</valorTotal><valorDolares>19.24</valorDolares></mercancia><mercancia><descripcionGenerica>SELECTORES</descripcionGenerica><claveUnidadMedida>6</claveUnidadMedida><tipoMoneda>USD</tipoMoneda><cantidad>1</cantidad><valorUnitario>9.73</valorUnitario><valorTotal>9.73</valorTotal><valorDolares>9.73</valorDolares></mercancia><mercancia><descripcionGenerica>SELECTORES</descripcionGenerica><claveUnidadMedida>6</claveUnidadMedida><tipoMoneda>USD</tipoMoneda><cantidad>1</cantidad><valorUnitario>9.73</valorUnitario><valorTotal>9.73</valorTotal><valorDolares>9.73</valorDolares></mercancia><mercancia><descripcionGenerica>INTERRUPTORES</descripcionGenerica><claveUnidadMedida>6</claveUnidadMedida><tipoMoneda>USD</tipoMoneda><cantidad>1</cantidad><valorUnitario>183.23</valorUnitario><valorTotal>183.23</valorTotal><valorDolares>183.23</valorDolares></mercancia><mercancia><descripcionGenerica>SUJETADORES</descripcionGenerica><claveUnidadMedida>6</claveUnidadMedida><tipoMoneda>USD</tipoMoneda><cantidad>1</cantidad><valorUnitario>30.07</valorUnitario><valorTotal>30.07</valorTotal><valorDolares>30.07</valorDolares></mercancia><mercancia><descripcionGenerica>SUJETADORES</descripcionGenerica><claveUnidadMedida>6</claveUnidadMedida><tipoMoneda>USD</tipoMoneda><cantidad>1</cantidad><valorUnitario>55.91</valorUnitario><valorTotal>55.91</valorTotal><valorDolares>55.91</valorDolares></mercancia></mercancias></factura></facturas><emisor><tipoIdentificador>0</tipoIdentificador><identificacion>421448821</identificacion><nombre>VAN METER INC</nombre><domicilio><calle>30 ND AVE SW</calle><numeroExterior>915</numeroExterior><numeroInterior>S/N</numeroInterior><colonia>.</colonia><municipio>CEDAR RAPIDS</municipio><entidadFederativa>IOWA</entidadFederativa><pais>USA</pais><codigoPostal>52404</codigoPostal></domicilio></emisor><destinatario><tipoIdentificador>1</tipoIdentificador><identificacion>GSY110601FD4</identificacion><nombre>GENESIS-ICESA SYSTEMS S DE RL DE CV</nombre><domicilio><calle>TOMAS ALBA EDISON</calle><numeroExterior>7</numeroExterior><colonia>ZONA INDUSTRIAL</colonia><municipio>SAN JUAN DEL RIO</municipio><entidadFederativa>QUERETARO</entidadFederativa><pais>MEX</pais><codigoPostal>76802</codigoPostal></domicilio></destinatario></cove></resultadoBusqueda></response></ConsultarEdocumentResponse></S:Body></S:Envelope>